neoadmin/__init__.py
neoadmin-0.0.2.dist-info/LICENSE
neoadmin-0.0.2.dist-info/METADATA
neoadmin-0.0.2.dist-info/WHEEL
neoadmin-0.0.2.dist-info/RECORD
